{
  "mappings": {
    "synonyms": {
      "properties": {
        "category": {
          "type": "text",
          "analyzer": "nostem"
        },
        "contentid": {
          "type": "keyword"
        },
        "is_exact": {
          "type": "boolean"
        },
        "is_negated": {
          "type": "boolean"
        },
        "language": {
          "type": "keyword"
        },
        "synonym": {
          "type": "text",
          "analyzer": "nostem"
        },
        "tokencount": {
          "type": "integer"
        }
      }
    },
    "categorydisplay": {
      "properties": {
        "contentid": {
          "type": "keyword"
        },
        "content": {
          "type": "text",
          "index": "false"
        }
      }
    }
  }
}
